actagent.py
explanagent.py
loadagent.py
prepagent.py
priceagent.py
usagent.py
xrecagent.py
recsagent-4.0.0.dist-info/LICENSE.txt
recsagent-4.0.0.dist-info/METADATA
recsagent-4.0.0.dist-info/WHEEL
recsagent-4.0.0.dist-info/top_level.txt
recsagent-4.0.0.dist-info/RECORD
